alcov/__init__.py
alcov/amplicon_coverage.py
alcov/analyze.py
alcov/artic_amplicons.py
alcov/cmds.py
alcov/command_line.py
alcov/consensus.py
alcov/constellations.py
alcov/convert_mutations.py
alcov/lineages.py
alcov/make_constellations.py
alcov/mutations.py
alcov/precompute.py
alcov/sars_cov_2.py
alcov-1.1.11.dist-info/METADATA
alcov-1.1.11.dist-info/WHEEL
alcov-1.1.11.dist-info/entry_points.txt
alcov-1.1.11.dist-info/top_level.txt
alcov-1.1.11.dist-info/RECORD
