Metadata-Version: 2.1
Name: alcov
Version: 1.1.11
Summary: Identify frequencies of concerning mutations from aligned reads
Home-page: https://github.com/Ellmen/alcov
Author: Isaac Ellmen
Author-email: isaac.ellmen@uwaterloo.ca
Maintainer: Jenn Knapp
Maintainer-email: jenn.knapp@uwaterloo.ca
Requires-Dist: fire
Requires-Dist: numpy
Requires-Dist: pandas
Requires-Dist: scikit-learn >=0.24
Requires-Dist: matplotlib
Requires-Dist: seaborn
Requires-Dist: pysam
